my_package/__init__.py
my_package/module1.py
my_package/module2.py
unique_pdf_reader-0.1.0.dist-info/METADATA
unique_pdf_reader-0.1.0.dist-info/WHEEL
unique_pdf_reader-0.1.0.dist-info/entry_points.txt
unique_pdf_reader-0.1.0.dist-info/top_level.txt
unique_pdf_reader-0.1.0.dist-info/RECORD
