Metadata-Version: 2.1
Name: unique_pdf_reader
Version: 0.1.0
Summary: A package to read PDF files aloud
Requires-Dist: PyPDF2
Requires-Dist: pyttsx3
